{
    "隔日沖名單": {
        "2032": "新鋼",
        "6443": "元晶",
        "3059": "華晶科",
        "1459": "聯發",
        "2027": "大成鋼",
        "2014": "中鴻"
    },
    "攻擊K名單": {
        "6190": "萬泰科",
        "2852": "第一保",
        "2408": "南亞科",
        "1712": "興農",
        "1515": "力山",
        "2002": "中鋼",
        "1101": "台泥",
        "2851": "中再保",
        "3162": "精確",
        "9907": "統一實",
        "4510": "高鋒",
        "1314": "中石化",
        "1459": "聯發",
        "2014": "中鴻",
        "4534": "慶騰",
        "6431": "光麗-KY",
        "2032": "新鋼",
        "2908": "特力",
        "3059": "華晶科",
        "2017": "官田鋼",
        "6185": "幃翔",
        "2867": "三商壽",
        "2641": "正德",
        "1307": "三芳",
        "5608": "四維航",
        "2010": "春源",
        "2891": "中信金",
        "2020": "美亞",
        "2027": "大成鋼"
    }
}