{
    "波段(縮口突破)": {
        "1514": "亞力",
        "3162": "精確",
        "6488": "環球晶",
        "2049": "上銀",
        "8043": "蜜望實",
        "5315": "光聯",
        "2454": "聯發科",
        "6415": "矽力*-KY",
        "3264": "欣銓",
        "8028": "昇陽半導體",
        "8299": "群聯",
        "8088": "品安",
        "5351": "鈺創",
        "8150": "南茂",
        "8112": "至上",
        "3236": "千如",
        "2365": "昆盈",
        "2342": "茂矽",
        "6223": "旺矽",
        "1608": "華榮",
        "3149": "正達",
        "6290": "良維",
        "3376": "新日興",
        "6217": "中探針",
        "2451": "創見",
        "2457": "飛宏",
        "3708": "上緯投控",
        "2401": "凌陽",
        "2606": "裕民"
    }
}