{
    "隔日沖名單": {
        "3093": "港建*",
        "4722": "國精化",
        "6283": "淳安",
        "4157": "太景*-KY",
        "1802": "台玻",
        "6134": "萬旭",
        "3528": "安馳",
        "2408": "南亞科"
    },
    "攻擊K名單": {
        "8155": "博智",
        "3093": "港建*",
        "3661": "世芯-KY",
        "4722": "國精化",
        "4977": "眾達-KY",
        "2820": "華票",
        "6235": "華孚",
        "1802": "台玻",
        "6283": "淳安",
        "6134": "萬旭",
        "6188": "廣明",
        "6698": "旭暉應材",
        "6142": "友勁",
        "3528": "安馳",
        "8271": "宇瞻",
        "4714": "永捷",
        "3217": "優群",
        "1810": "和成"
    }
}