{
    "波段(縮口突破)": {
        "1440": "南紡",
        "6147": "頎邦",
        "3715": "定穎投控",
        "3006": "晶豪科",
        "6182": "合晶",
        "3673": "TPK-KY",
        "2409": "友達",
        "5351": "鈺創",
        "6209": "今國光",
        "2374": "佳能",
        "3005": "神基",
        "4919": "新唐",
        "2478": "大毅",
        "2376": "技嘉",
        "2324": "仁寶",
        "2371": "大同",
        "4142": "國光生",
        "3019": "亞光",
        "2328": "廣宇",
        "8069": "元太",
        "2455": "全新",
        "9802": "鈺齊-KY",
        "4958": "臻鼎-KY",
        "3260": "威剛",
        "2360": "致茂",
        "1605": "華新",
        "6187": "萬潤",
        "3357": "臺慶科",
        "8054": "安國",
        "3694": "海華",
        "5381": "合正",
        "3707": "漢磊",
        "2301": "光寶科",
        "2342": "茂矽",
        "3305": "昇貿",
        "6488": "環球晶",
        "3062": "建漢"
    }
}