{
  "更新時間": "2026-04-21_17-22-15",
  "放空日內波": {
    "3709": "鑫聯大投控",
    "8088": "品安",
    "2312": "金寶",
    "3041": "揚智",
    "3419": "譁裕",
    "6202": "盛群",
    "6806": "森崴能源"
  },
  "縮口": {
    "3188": "鑫龍騰",
    "3211": "順達",
    "8027": "鈦昇",
    "8096": "擎亞",
    "1477": "聚陽",
    "1529": "樂事綠能",
    "1582": "信錦",
    "2344": "華邦電",
    "2355": "敬鵬",
    "2515": "中工",
    "3005": "神基",
    "3029": "零壹",
    "3062": "建漢",
    "3715": "定穎投控",
    "4906": "正文",
    "6277": "宏正",
    "6770": "力積電",
    "8110": "華東"
  }
}